{
  "title": "Regain access to Amazon Q CLI in CloudShell with This Simple Trick",
  "views": 27,
  "comments": 0,
  "reactions": 1,
  "org_username": "aws-builders",
  "referrers": [
    {
      "domain": null,
      "count": 11
    },
    {
      "domain": "t.co",
      "count": 10
    },
    {
      "domain": "dev.to",
      "count": 5
    },
    {
      "domain": "github.com",
      "count": 1
    }
  ],
  "breakdown": [
    {
      "date": "2025-08-02",
      "views": 4,
      "comments": 0,
      "reactions": 0
    },
    {
      "date": "2025-08-03",
      "views": 3,
      "comments": 0,
      "reactions": 0
    },
    {
      "date": "2025-08-04",
      "views": 18,
      "comments": 0,
      "reactions": 1
    },
    {
      "date": "2025-08-05",
      "views": 2,
      "comments": 0,
      "reactions": 0
    },
    {
      "date": "2025-08-06",
      "views": 0,
      "comments": 0,
      "reactions": 0
    }
  ]
}