{
  "title": "I Squeezed My $1k Monthly OpenClaw API Bill with ~$20/Month in AWS Credits \u2014 Here's the Exact Setup",
  "views": 1566,
  "comments": 0,
  "reactions": 13,
  "org_username": "aws-builders",
  "referrers": [
    {
      "domain": "google.com",
      "count": 963
    },
    {
      "domain": null,
      "count": 487
    },
    {
      "domain": "dev.to",
      "count": 43
    },
    {
      "domain": "bing.com",
      "count": 12
    },
    {
      "domain": "perplexity.ai",
      "count": 11
    },
    {
      "domain": "yandex.com",
      "count": 10
    },
    {
      "domain": "google.ru",
      "count": 10
    },
    {
      "domain": "com.slack",
      "count": 10
    },
    {
      "domain": "google.com.hk",
      "count": 10
    },
    {
      "domain": "brave.com",
      "count": 10
    }
  ],
  "breakdown": [
    {
      "date": "2026-02-21",
      "views": 158,
      "comments": 0,
      "reactions": 2
    },
    {
      "date": "2026-02-22",
      "views": 359,
      "comments": 0,
      "reactions": 3
    },
    {
      "date": "2026-02-23",
      "views": 336,
      "comments": 0,
      "reactions": 5
    },
    {
      "date": "2026-02-24",
      "views": 329,
      "comments": 0,
      "reactions": 3
    },
    {
      "date": "2026-02-25",
      "views": 383,
      "comments": 0,
      "reactions": 0
    },
    {
      "date": "2026-02-26",
      "views": 1,
      "comments": 0,
      "reactions": 0
    }
  ]
}